[
	{
		"name": "Fedora",
		"description": "Fedora is a polished, easy to use operating system for laptop and desktop computers.",
		"desktops": ["GNOME","KDE","XFCE","Cinnamon","i3","LXQt","MATE"],
		"scores":	{
			"Experience":	1.5,
			"Gaming": 		2.5,
			"Modern": 		3,
			"Options": 		2.5,
			"Keyboard": 	2,
			"Pretty": 		2.5,
			"Ins_Complex": 	1.5,
			"PM_Terminal":	1.5,
			"Privacy": 		3,
			"Hard_Freedom": 2,
			"Adventure": 	2,
			"Upd_Regular": 	2.5,
			"Nvidia": 		2.5,
			"Extra_Score": 	3
		}
	},
	{
		"name": "Nobara",
		"description":"The Nobara Project, is a modified version of Fedora Linux with user-friendly fixes added to it.",
		"desktops": ["GNOME","KDE"],
		"scores":	{
			"Experience":	1,
			"Gaming": 		3,
			"Modern": 		2.5,
			"Options": 		2,
			"Keyboard": 	2,
			"Pretty": 		2.5,
			"Ins_Complex": 	1,
			"PM_Terminal":	1,
			"Privacy": 		3,
			"Hard_Freedom": 1.5,
			"Adventure": 	1.5,
			"Upd_Regular": 	2,
			"Nvidia": 		3,
			"Extra_Score": 	2
		}
	},
	{
		"name": "Linux Mint",
		"description": "Linux Mint is designed to work out of the box and comes fully equipped with the apps most people need.",
		"desktops": ["Cinnamon","XFCE","MATE"],
		"scores":	{
			"Experience":	1,
			"Gaming": 		1.5,
			"Modern": 		1.5,
			"Options": 		2,
			"Keyboard": 	1,
			"Pretty": 		2,
			"Ins_Complex": 	1,
			"PM_Terminal":	1,
			"Privacy": 		3,
			"Hard_Freedom": 1.5,
			"Adventure": 	1,
			"Upd_Regular": 	1.5,
			"Nvidia": 		2.5,
			"Extra_Score": 	2
		}
	},
	{
		"name": "LMDE",
		"description":"LMDE aims to be as similar as possible to Linux Mint, but without using Ubuntu. The package base is provided by Debian instead.",
		"desktops": ["Cinnamon"],
		"scores":	{
			"Experience":	1,
			"Gaming": 		1,
			"Modern": 		1.5,
			"Options": 		2,
			"Keyboard": 	2,
			"Pretty": 		2,
			"Ins_Complex": 	1,
			"PM_Terminal":	1,
			"Privacy": 		3,
			"Hard_Freedom": 1.5,
			"Adventure": 	1,
			"Upd_Regular": 	1,
			"Nvidia": 		2,
			"Extra_Score": 	1.5
		}
	},
	{
		"name": "Ubuntu",
		"description":"The open source desktop operating system that powers millions of PCs and laptops around the world.",
		"desktops": ["GNOME", "KDE", "XFCE","LXQt"],
		"scores":	{
			"Experience":	1,
			"Gaming": 		1.5,
			"Modern": 		2,
			"Options": 		1,
			"Keyboard": 	1,
			"Pretty": 		3,
			"Ins_Complex": 	1,
			"PM_Terminal":	1,
			"Privacy": 		1.5,
			"Hard_Freedom": 	1,
			"Adventure": 	1.5,
			"Upd_Regular": 	1.5,
			"Nvidia": 		2,
			"Extra_Score": 	1
		}
	},
	{
		"name": "Pop!_OS",
		"description":"Pop!_OS is designed to remove obstacles from your plate. Apps and windows respond quickly to your actions, and multi-monitor use feels intuitive and smooth.",
		"desktops": ["Cosmic"],
		"scores":	{
			"Experience":	1.5,
			"Gaming": 		2.5,
			"Modern": 		2,
			"Options": 		1,
			"Keyboard": 	1.2,
			"Pretty": 		3,
			"Ins_Complex": 	1,
			"PM_Terminal":	1,
			"Privacy": 		3,
			"Hard_Freedom": 	1.5,
			"Adventure": 	2,
			"Upd_Regular": 	1,
			"Nvidia": 		2.5,
			"Extra_Score": 	1.5
		}
	},
	{
		"name": "Arch Linux",
		"description":"A lightweight and flexible Linux distribution that tries to Keep It Simple.",
		"desktops": ["GNOME","KDE","XFCE","i3","Hyprland","MATE","Niri","Cosmic","LXDE", "DWM"],
		"scores":	{
			"Experience":	2.5,
			"Gaming": 		3,
			"Modern": 		2.5,
			"Options": 		3,
			"Keyboard": 	2,
			"Pretty": 		2,
			"Ins_Complex": 	2.5,
			"PM_Terminal":	3,
			"Privacy": 		3,
			"Hard_Freedom": 3,
			"Adventure": 	2,
			"Upd_Regular": 	3,
			"Nvidia": 		2.5,
			"Extra_Score": 	3
		}
	},
	{
		"name": "Omarchy",
		"description":"Beautiful, Modern & Opinionated Distribution based on Arch Linux",
		"desktops": ["Hyprland"],
		"scores":	{
			"Experience":	2.5,
			"Gaming": 		3,
			"Modern": 		2.5,
			"Options": 		2,
			"Keyboard": 	2,
			"Pretty": 		2,
			"Ins_Complex": 	2,
			"PM_Terminal":	3,
			"Privacy": 		3,
			"Hard_Freedom": 2,
			"Adventure": 	2.5,
			"Upd_Regular": 	3,
			"Nvidia": 		2.5,
			"Extra_Score": 	1
		}
	},
	{
		"name": "CachyOS",
		"description":"A distribution based on Arch Linux, with Gaming optimizations and tools included.",
		"desktops": ["GNOME","KDE","XFCE","Hyprland","MATE","Niri","Cosmic"],
		"scores":	{
			"Experience":	2.5,
			"Gaming": 		3,
			"Modern": 		2.5,
			"Options": 		2.5,
			"Keyboard": 	2,
			"Pretty": 		2,
			"Ins_Complex": 	2,
			"PM_Terminal":	2,
			"Privacy": 		3,
			"Hard_Freedom": 	3,
			"Adventure": 	2,
			"Upd_Regular": 	3,
			"Nvidia": 		3,
			"Extra_Score": 	2.5
		}
	},
	{
		"name": "Debian",
		"description":"Debian is a Linux distribution that's composed entirely of free and open-source software.",
		"desktops": ["GNOME","KDE","XFCE","MATE","i3","LXQt"],
		"scores":	{
			"Experience":	3,
			"Gaming": 		1.5,
			"Modern": 		1,
			"Options": 		2,
			"Keyboard": 	2,
			"Pretty": 		1.5,
			"Ins_Complex": 	2,
			"PM_Terminal":	2,
			"Privacy": 		3,
			"Hard_Freedom": 	1.5,
			"Adventure": 	1,
			"Upd_Regular": 	1,
			"Nvidia": 		1.5,
			"Extra_Score": 	3
		}
	},		
	{
		"name": "Bazzite",
		"description":"Bazzite makes gaming and everyday use smoother and simpler across desktop PCs, handhelds, tablets, and home theater PCs.",
		"desktops": ["GNOME","KDE"],
		"scores":	{
			"Experience":	1,
			"Gaming": 		3,
			"Modern": 		3,
			"Options": 		1,
			"Keyboard": 	1,
			"Pretty": 		3,
			"Ins_Complex": 	1,
			"PM_Terminal":	1,
			"Privacy": 		3,
			"Hard_Freedom": 	1,
			"Adventure": 	1.5,
			"Upd_Regular": 	2,
			"Nvidia": 		3,
			"Extra_Score": 	3
		}
	},		
	{
		"name": "Fedora Atomic",
		"description":"Immutable distro based on Fedora.",
		"desktops": ["GNOME","KDE","Sway"],
		"scores":	{
			"Experience":	2,
			"Gaming": 		2,
			"Modern": 		3,
			"Options": 		2,
			"Keyboard": 	2,
			"Pretty": 		3,
			"Ins_Complex": 	2,
			"PM_Terminal":	1,
			"Privacy": 		3,
			"Hard_Freedom": 	1.5,
			"Adventure": 	2,
			"Upd_Regular": 	3,
			"Nvidia": 		2,
			"Extra_Score": 	1.5
		}
	},
	{
		"name": "Gentoo",
		"description":"Gentoo, a highly flexible, source-based Linux distribution. Similar to Arch Linux but you'll need to compile a lot.",
		"desktops": ["GNOME","KDE","XFCE","i3","Hyprland","MATE","Niri","Cosmic","LXDE"],
		"scores":	{
			"Experience":	3,
			"Gaming": 		2,
			"Modern": 		2.5,
			"Options": 		3,
			"Keyboard": 	2.5,
			"Pretty": 		2,
			"Ins_Complex": 	3,
			"PM_Terminal":	3,
			"Privacy": 		3,
			"Hard_Freedom": 	3,
			"Adventure": 	3,
			"Upd_Regular": 	3,
			"Nvidia": 		2,
			"Extra_Score": 	1.5
		}
	},		
	{
		"name": "NixOS",
		"description":"Nix is a tool that takes a unique approach to package management and system configuration. Learn how to make reproducible, declarative and reliable systems.",
		"desktops": ["GNOME","KDE","XFCE","i3","Hyprland","MATE","Niri","Cosmic","LXDE"],
		"scores":	{
			"Experience":	3,
			"Gaming": 		2,
			"Modern": 		2,
			"Options": 		3,
			"Keyboard": 	2.5,
			"Pretty": 		2,
			"Ins_Complex": 	3,
			"PM_Terminal":	3,
			"Privacy": 		3,
			"Hard_Freedom": 	1,
			"Adventure": 	2.5,
			"Upd_Regular": 	2,
			"Nvidia": 		2,
			"Extra_Score": 	2
		}
	},
	{
			"name": "Void",
			"description":"Unlike trillions of other existing distros, Void is not a modification of an existing distribution. Void's package manager and build system have been written from scratch.",
			"desktops": ["KDE","XFCE","i3","Hyprland","MATE","LXDE","DWM"],
			"scores":	{
				"Experience":	2.5,
				"Gaming": 		1.5,
				"Modern": 		2,
				"Options": 		3,
				"Keyboard": 	2,
				"Pretty": 		2,
				"Ins_Complex": 	2.5,
				"PM_Terminal":	3,
				"Privacy": 		3,
				"Hard_Freedom": 	3,
				"Adventure": 	3,
				"Upd_Regular": 	3,
				"Nvidia": 		1,
				"Extra_Score": 	2
			}
	},
	{
		"name": "Slackware",
		"description":"A very traditional but interesting Distribution.",
		"desktops": ["KDE","XFCE","i3","Hyprland","MATE","LXDE"],
		"scores":	{
			"Experience":	3,
			"Gaming": 		1,
			"Modern": 		1,
			"Options": 		3,
			"Keyboard": 	1,
			"Pretty": 		1,
			"Ins_Complex": 	3,
			"PM_Terminal":	3,
			"Privacy": 		3,
			"Hard_Freedom": 3,
			"Adventure": 	3,
			"Upd_Regular": 	1,
			"Nvidia": 		1,
			"Extra_Score": 	0.5
		}
	},		
	{
		"name": "Zorin OS",
		"description":"A distribution aimed at new users. Has questionable marketing.",
		"desktops": ["GNOME","XFCE"],
		"scores":	{
			"Experience":	1,
			"Gaming": 		1,
			"Modern": 		1.5,
			"Options": 		3,
			"Keyboard": 	1,
			"Pretty": 		3,
			"Ins_Complex": 	1,
			"PM_Terminal":	1,
			"Privacy": 		2,
			"Hard_Freedom": 	2,
			"Adventure": 	1,
			"Upd_Regular": 	1,
			"Nvidia": 		1.5,
			"Extra_Score": 	0
		}
	},		
	{
		"name": "OpenSUSE Leap",
		"description":"Builds on its hybrid approach of combining source from SUSE Linux Enterprise (SLE) with community developments, delivering a level of stability unmatched by other Linux distributions.",
		"desktops": ["GNOME","KDE","XFCE"],
		"scores":	{
			"Experience":	2,
			"Gaming": 		2,
			"Modern": 		2.5,
			"Options": 		2,
			"Keyboard": 	2,
			"Pretty": 		2,
			"Ins_Complex": 	2,
			"PM_Terminal":	3,
			"Privacy": 		3,
			"Hard_Freedom": 	2,
			"Adventure": 	2,
			"Upd_Regular": 	1.5,
			"Nvidia": 		1.5,
			"Extra_Score": 	2
		}
	},
	{
		"name": "OpenSUSE Tumbleweed",
		"description":"With Tumbleweed you don't have to take difficult decisions about things you value, either freedom or safety, either control or security, technology or stability -- Tumbleweed lets you have your cake and eat it too!",
		"desktops": ["GNOME","KDE","XFCE"],
		"scores":	{
			"Experience":	2,
			"Gaming": 		2,
			"Modern": 		2.5,
			"Options": 		2,
			"Keyboard": 	2,
			"Pretty": 		2,
			"Ins_Complex": 	2,
			"PM_Terminal":	3,
			"Privacy": 		3,
			"Hard_Freedom": 2,
			"Adventure": 	2,
			"Upd_Regular": 	3,
			"Nvidia": 		1.7,
			"Extra_Score": 	2
		}
	},
	{
		"name": "EndeavourOS",
		"description":"Start your Endeavour with a lightweight Arch-based, terminal centric system ready to personalise and a stellar community at your side.",
		"desktops": ["GNOME","KDE","MATE"],
		"scores":	{
			"Experience":	2.52,
			"Gaming": 		3,
			"Modern": 		2,
			"Options": 		3,
			"Keyboard": 	2,
			"Pretty": 		3,
			"Ins_Complex": 	2,
			"PM_Terminal":	2,
			"Privacy": 		3,
			"Hard_Freedom": 2.5,
			"Adventure": 	2,
			"Upd_Regular": 	2.5,
			"Nvidia": 		3,
			"Extra_Score": 	2
		}
	},				
	{
		"name": "Manjaro",
		"description":"Taking the raw power and flexibility of Arch Linux and making it more accessible for a greater audience.",
		"desktops": ["GNOME","XFCE","KDE","MATE"],
		"scores":	{
			"Experience":	2.5,
			"Gaming": 		3,
			"Modern": 		2,
			"Options": 		3,
			"Keyboard": 	2,
			"Pretty": 		2,
			"Ins_Complex": 	2,
			"PM_Terminal":	3,
			"Privacy": 		3,
			"Hard_Freedom": 3,
			"Adventure": 	1.5,
			"Upd_Regular": 	3,
			"Nvidia": 		3,
			"Extra_Score": 	0
		}				
	}	
]
